dsldPy/Utils.py
dsldPy/__init__.py
dsldPy/dsldPyBnLearn.py
dsldPy/dsldPyConditDisparity.py
dsldPy/dsldPyConfounders.py
dsldPy/dsldPyDensitybyS.py
dsldPy/dsldPyFairML.py
dsldPy/dsldPyFairUtils.py
dsldPy/dsldPyFreqPCoord.py
dsldPy/dsldPyFrequencybyS.py
dsldPy/dsldPyHunting.py
dsldPy/dsldPyLinear.py
dsldPy/dsldPyLogit.py
dsldPy/dsldPyML.py
dsldPy/dsldPyMatching.py
dsldPy/dsldPyQeFairML.py
dsldPy/dsldPyScatterPlot3D.py
dsldPy/dsldPyTakeALookAround.py
dsldpy-0.0.3.dist-info/METADATA
dsldpy-0.0.3.dist-info/WHEEL
dsldpy-0.0.3.dist-info/top_level.txt
dsldpy-0.0.3.dist-info/RECORD
