Metadata-Version: 2.4
Name: dsldPy
Version: 0.0.3
Summary: Python wrappers around the R 'dsld' package via rpy2
Author: A. Mittal, T. Abdullah, A. Ashok, B. Zarate Estrada, S. Martha, B. Ouattara, J. Tran, and N. Matloff
License-Expression: MIT
Keywords: dsld,rpy2,fair machine learning,statistics,confounder analysis
Classifier: Programming Language :: Python :: 3
Classifier: Operating System :: OS Independent
Classifier: Topic :: Scientific/Engineering
Requires-Python: >=3.8
Requires-Dist: pandas>=1.1
Requires-Dist: numpy>=1.20
Requires-Dist: Pillow>=8
Requires-Dist: pyreadr>=0.4
Requires-Dist: rpy2>=3.5
Requires-Dist: plotly>=5
Requires-Dist: ipython>=7
Requires-Dist: nbformat
Requires-Dist: scikit-learn
